{"cameraMode":{"drawMode":0,"name":"Shaded","section":"Shading Mode"},"sceneLighting":true,"audioPlay":false,"sceneViewState":{"m_AlwaysRefresh":false,"showFog":true,"showSkybox":true,"showFlares":true,"showImageEffects":true,"showParticleSystems":true,"showVisualEffectGraphs":true,"m_FxEnabled":true},"in2DMode":false,"pivot":{"x":-384.5031433105469,"y":-262.34783935546877,"z":131.66909790039063},"rotation":{"x":0.23498745262622834,"y":-0.5650046467781067,"z":0.1670629382133484,"w":0.773696780204773},"size":263.2353210449219,"orthographic":false}